torch_conv_gradfix/__init__.py
torch_conv_gradfix/conv_gradfix.py
torch_conv_gradfix/namespace.py
torch_conv_gradfix/utils.py
torch_conv_gradfix-0.1.0.dist-info/entry_points.txt
torch_conv_gradfix-0.1.0.dist-info/LICENSE
torch_conv_gradfix-0.1.0.dist-info/WHEEL
torch_conv_gradfix-0.1.0.dist-info/METADATA
torch_conv_gradfix-0.1.0.dist-info/RECORD
